{"type": "scene", "properties": {"height": 56.644295302013425, "width": 100.0, "baseExtent": [390711.4908745509, 1565295.0844226896, 471643.94845480565, 1611138.7046896259], "crs": "EPSG:32616", "proj": "+proj=utm +zone=16 +datum=WGS84 +units=m +no_defs", "rotation": 0, "wgs84Center": {"lat": 14.36525021375507, "lon": -87.6383071532903}, "zExaggeration": 2.5, "zShift": 0.0}, "layers": [{"type": "layer", "id": 0, "properties": {"name": "ComunidadesValleComayagua", "queryable": 1, "visible": true, "type": "point", "objType": "Sphere"}, "data": {"materials": [{"type": 0, "c": 5550154}], "blocks": [{"url": "./data/index/a0.json", "featureCount": 14}]}}, {"type": "layer", "id": 5, "properties": {"name": "Valle de Comayagua", "queryable": 1, "visible": true, "type": "polygon", "objType": "Polygon"}, "data": {"materials": [{"type": 0, "c": 16777215, "flat": 1, "ds": 1}], "blocks": [{"url": "./data/index/b0.json", "featureCount": 1}]}}, {"type": "layer", "id": 8, "properties": {"name": "Modelo Digital de Elevaciones", "queryable": 1, "visible": true, "type": "dem", "shading": true}, "data": [{"type": "block", "layer": 8, "block": 0, "width": 100.0, "height": 56.644295302013425, "translate": [0.0, 0.0, 0.0], "zShift": 0.0, "zScale": 0.003088995533739889, "material": {"type": 0, "image": {"url": "./data/index/c0.png"}, "ds": 1}, "grid": {"width": 266, "height": 151, "url": "./data/index/c0.bin"}, "sides": {"mtl": {"type": 0, "c": 13417386}}}]}]}